auxiliary.py
nkocr.py
ocr_product.py
ocr_table.py
nkocr-2.5.1.dist-info/LICENSE
nkocr-2.5.1.dist-info/METADATA
nkocr-2.5.1.dist-info/WHEEL
nkocr-2.5.1.dist-info/top_level.txt
nkocr-2.5.1.dist-info/RECORD
