Metadata-Version: 2.1
Name: nkocr
Version: 2.5.1
Summary: This is a module to make specifics OCRs          at food products and nutricional tables.
Home-page: https://github.com/Lucs1590/Nkocr
Download-URL: https://github.com/Lucs1590/Nkocr
Author: Lucas de Brito Silva
Author-email: lucasbsilva29@gmail.com
License: Apache License 2.0
Keywords: ocr,tesseract-ocr,nk,python3,python-3,food-products
Classifier: Natural Language :: English
Classifier: Programming Language :: Python
Classifier: Programming Language :: Python :: 3
Classifier: Operating System :: OS Independent
Classifier: Intended Audience :: Developers
Classifier: Intended Audience :: Science/Research
Classifier: Intended Audience :: Healthcare Industry
Classifier: Development Status :: 5 - Production/Stable
Classifier: License :: OSI Approved :: Apache Software License
Classifier: Topic :: Communications :: Email
Classifier: Topic :: Scientific/Engineering :: Artificial Intelligence
Classifier: Topic :: Scientific/Engineering :: Image Processing
Classifier: Topic :: Scientific/Engineering :: Image Recognition
Classifier: Topic :: Software Development :: Testing
Requires-Python: >=3.6
License-File: LICENSE
Requires-Dist: tesseract==0.1.3
Requires-Dist: pytesseract==0.3.10
Requires-Dist: requests==2.32.0
Requires-Dist: wheel==0.43.*
Requires-Dist: Pillow>=10.2.0
Requires-Dist: numpy==1.26.0
Requires-Dist: opencv-contrib-python==4.10.0.84
Requires-Dist: scikit-learn==1.5.0
Requires-Dist: gdown==5.1.0
Requires-Dist: imutils==0.5.4
Requires-Dist: symspellpy==6.7.7
Provides-Extra: dev
Requires-Dist: pytest>=3.7; extra == "dev"
Requires-Dist: pytest-socket==0.6.0; extra == "dev"
Requires-Dist: commitizen==3.10.0; extra == "dev"
Requires-Dist: pre-commit==3.4.0; extra == "dev"
